py_string_tool/__init__.py
py_string_tool/blackslash_replace.py
py_string_tool/cant_use_pst.py
py_string_tool/fix_bug_pst.py
py_string_tool/utils.py
py_string_tool/utils_pst.py
py_string_tool-0.1.4.dist-info/METADATA
py_string_tool-0.1.4.dist-info/WHEEL
py_string_tool-0.1.4.dist-info/top_level.txt
py_string_tool-0.1.4.dist-info/RECORD
